{
    "+ Add User": "Ajouter un utilisateur",
    "1 minute": "1 minute",
    "10 items": "10 éléments",
    "10 seconds": "10 secondes",
    "1080p (10 Mbps)": "1080p (10 Mbps)",
    "1080p (20 Mbps)": "1080p (20 Mbps)",
    "12-Hour": "Format 12h",
    "15 items": "15 éléments",
    "2 minutes": "2 minutes",
    "20 seconds": "20 secondes",
    "24-Hour": "Format 24h",
    "3 minutes": "3 minutes",
    "30 seconds": "30 secondes",
    "360p (1 Mbps)": "360p (1 Mbps)",
    "480p (2 Mbps)": "480p (2 Mbps)",
    "4K (60 Mbps)": "4K (60 Mbps)",
    "4K AVAILABLE": "4K DISPONIBLE",
    "4K DECLINED": "4K REJETÉE",
    "4K PARTIALLY AVAILABLE": "4K PARTIELLEMENT DISPONIBLE",
    "4K PENDING": "4K EN ATTENTE",
    "4K PROCESSING": "4K EN COURS",
    "5 items": "5 éléments",
    "5 minutes": "5 minutes",
    "5 seconds": "5 secondes",
    "720p (4 Mbps)": "720p (4 Mbps)",
    "720p (8 Mbps)": "720p (8 Mbps)",
    "90 seconds": "90 secondes",
    "A network error occurred. Check your connection.": "Erreur réseau. Veuillez vérifier votre connexion.",
    "About": "À propos",
    "Absolute": "Absolu",
    "Absolute Position": "Position précise",
    "Account": "Compte",
    "Active": "Actif",
    "Add New Server": "Ajouter un serveur",
    "Add to Playlist": "Ajouter à la playlist",
    "Added to playlist": "Ajouté à la playlist",
    "Adding user...": "Ajout de l'utilisateur...",
    "Adding…": "Ajout…",
    "Age Rating Filter": "Classification",
    "Albums": "Albums",
    "All": "Tout",
    "All Channels": "Toutes les chaînes",
    "All Libraries": "Toutes les bibliothèques",
    "All items": "Tous les éléments",
    "Always": "Toujours",
    "An unknown playback error occurred.": "Une erreur de lecture inconnue est survenue.",
    "App Version": "Version de l'application",
    "App behavior, navigation, and home screen": "Comportement et interface",
    "App info and device capabilities": "Infos système et capacités",
    "Appearance": "Apparence",
    "Appearance, theme, and screensaver": "Thèmes et économiseur d'écran",
    "Appearances": "Apparences",
    "Application": "Application",
    "Approved": "Approuvé",
    "Are you sure you want to exit?": "Voulez-vous vraiment quitter ?",
    "Are you sure you want to remove {username} from {serverName}?": "Supprimer {username} de {serverName} ?",
    "Artist": "Artiste",
    "Artists": "Artistes",
    "Ask to Skip": "Demander avant de passer",
    "Audio": "Audio",
    "Audio Bitrate": "Débit audio",
    "Audio Codecs": "Codecs audio",
    "Auto": "Auto",
    "Auto (No limit)": "Auto (Illimité)",
    "Auto Login": "Connexion automatique",
    "Auto Play Next": "Lecture auto suivante",
    "Auto Skip": "Passage automatique",
    "Auto-play and next episode prompt": "Lecture auto et suggestions",
    "Automatically play the next episode": "Lire automatiquement l'épisode suivant",
    "Automatically play trailer previews in the featured media bar": "Lecture auto des bandes-annonces à la une",
    "Automatically sign in on app launch": "Connexion automatique au démarrage",
    "Available": "Disponible",
    "BLACKLISTED": "LISTE NOIRE",
    "Back": "Retour",
    "Back Close": "Retour / Fermer",
    "Backdrop": "Arrière-plan",
    "Background Color": "Couleur de fond",
    "Background Opacity": "Opacité du fond",
    "Background art and blur": "Image de fond et flou",
    "Biography": "Biographie",
    "Bit Depth": "Profondeur de bits",
    "Bitrate": "Débit",
    "Black": "Noir",
    "Blacklisted": "Sur liste noire",
    "Blue": "Bleu",
    "Born": "Naissance",
    "Bottom": "Bas",
    "Brown": "Marron",
    "Browse": "Parcourir",
    "Browse Movies by Genre": "Films par genre",
    "Browse TV by Genre": "Séries par genre",
    "Browse by Network": "Par chaîne",
    "Browse by Studio": "Par studio",
    "Budget": "Budget",
    "Burn-in protection": "Protection anti-marquage",
    "Cancel": "Annuler",
    "Cancel Recording": "Annuler l'enregistrement",
    "Cancel Request": "Annuler la demande",
    "Capabilities": "Capacités",
    "Card Focus Zoom": "Zoom sur la sélection",
    "Card size": "Taille des vignettes",
    "Cast": "Casting",
    "Cast & Crew": "Casting et équipe",
    "Change Server": "Changer de serveur",
    "Channel:": "Chaîne :",
    "Channels": "Chaînes",
    "Chapters": "Chapitres",
    "Charcoal": "Anthracite",
    "Checking Moonfin plugin...": "Vérification du plugin Moonfin...",
    "Choose which libraries to hide (syncs across all clients)": "Sélection des bibliothèques à masquer",
    "Clock Display": "Affichage de l'horloge",
    "Clock, auto login": "Horloge et connexion",
    "Close": "Fermer",
    "Codec": "Codec",
    "Collections": "Collections",
    "Combine content from all servers into a single view": "Vue unifiée de tous les serveurs",
    "Combine into a single row": "Fusionner sur une seule ligne",
    "Comic": "BD",
    "Community": "Communauté",
    "Compact": "Compact",
    "Configure Home Rows": "Configurer l'accueil",
    "Connect": "Connexion",
    "Connect for ratings, sync, and {seerrLabel} proxy": "Notes, synchro et proxy {seerrLabel}",
    "Connect to Server": "Se connecter au serveur",
    "Connected successfully!": "Connexion réussie !",
    "Connected to {serverName}! Loading users...": "Connecté à {serverName}. Chargement...",
    "Connected via Moonfin": "Connecté via Moonfin",
    "Connected via Moonfin!": "Connecté via Moonfin !",
    "Connecting...": "Connexion...",
    "Connection and version": "Connexion et version",
    "Container": "Conteneur",
    "Containers": "Conteneurs",
    "Content Type": "Type de contenu",
    "Continue Watching": "Reprendre la lecture",
    "Continue with Options": "Options de lecture",
    "Countdown Timer": "Minuteur",
    "Create": "Créer",
    "Create New Playlist": "Nouvelle playlist",
    "Creating…": "Création…",
    "Current": "Actuel",
    "Current:": "Actuel :",
    "Customize which rows appear on home screen": "Personnaliser les lignes de l'accueil",
    "Cyan": "Cyan",
    "DECLINED": "REJETÉE",
    "Dark Blue": "Bleu foncé",
    "Dark Green": "Vert foncé",
    "Dark Grey": "Gris foncé",
    "Dark Red": "Rouge foncé",
    "Debugging": "Débogage",
    "Declined": "Rejetée",
    "Default": "Par défaut",
    "Delete": "Supprimer",
    "Details Backdrop Blur": "Flou d'arrière-plan (détails)",
    "Detected Variant": "Variante détectée",
    "Device": "Appareil",
    "Dimming Level": "Niveau d'assombrissement",
    "Direct Play PGS Subtitles": "Lecture directe (PGS)",
    "Director": "Réalisateur",
    "Disabled": "Désactivé",
    "Disabled by Admin": "Désactivé par l'administrateur",
    "Discography": "Discographie",
    "Disconnect": "Déconnexion",
    "Discover": "Découvrir",
    "Display": "Affichage",
    "Display a moving clock during screensaver": "Horloge mobile pendant l'économie",
    "Display item description when paused": "Infos du média sur pause",
    "Display source names below rating scores": "Afficher la source sous les notes",
    "Display the featured media bar on home screen": "Bandeau à la une sur l'accueil",
    "Download": "Télécharger",
    "Download Location": "Emplacement",
    "Download Subtitles": "Télécharger les sous-titres",
    "Downloading": "Téléchargement",
    "Duration:": "Durée :",
    "Embedded": "Intégré",
    "Enable Plugin": "Activer le plugin",
    "Enable Ratings": "Activer les notes",
    "Enable Screensaver": "Activer l'économiseur",
    "Enable the Moonfin plugin to access ratings, settings sync, and {seerrLabel} proxy features. The plugin must be installed on your Jellyfin server.": "Activez Moonfin pour les notes et la synchro. Nécessite l'installation sur le serveur.",
    "Enable/disable and reorder the rows that appear on your home screen.": "Gérer l'ordre et l'affichage des lignes d'accueil.",
    "Enabled by Admin": "Activé par l'administrateur",
    "Ends at {time}": "Fin à {time}",
    "Enter Password": "Saisir le mot de passe",
    "Enter the code on another device or authorize in the Jellyfin dashboard": "Saisissez le code sur un autre appareil",
    "Enter this code on another device or authorize in Jellyfin dashboard:": "Entrez ce code sur un autre appareil :",
    "Enter {seerrLabel} password": "Mot de passe {seerrLabel}",
    "Enter {seerrLabel} username": "Utilisateur {seerrLabel}",
    "Episode": "Épisode",
    "Episode Ratings": "Notes des épisodes",
    "Episode rating settings": "Réglages des notes",
    "Episodes": "Épisodes",
    "Episodes Only": "Épisodes uniquement",
    "Exit": "Quitter",
    "Exit Moonfin?": "Quitter Moonfin ?",
    "Extended": "Étendu",
    "External": "Externe",
    "Extra Large": "Très grand",
    "FAVORITES": "FAVORIS",
    "Failed to cancel request": "Erreur lors de l'annulation",
    "Failed to load details": "Erreur de chargement",
    "Failed to load media": "Erreur de chargement du média",
    "Failed to load requests": "Erreur lors du chargement des demandes",
    "Failed to seek - please try again": "Échec de la recherche, réessayez",
    "Fall": "Automne",
    "Favorite": "Favori",
    "Favorited": "Ajouté aux favoris",
    "Favorites": "Favoris",
    "Favorites Only": "Favoris uniquement",
    "Featured Media Bar": "Bandeau à la une",
    "Featured content and trailers": "Contenu à la une et bandes-annonces",
    "Filmography": "Filmographie",
    "Filter": "Filtrer",
    "Filters": "Filtres",
    "Find movies, TV shows, music, and more": "Rechercher films, séries, musique...",
    "Firmware": "Firmware",
    "First Air Date": "Première diffusion",
    "Focus Color": "Couleur de sélection",
    "Folder view": "Vue par dossier",
    "Force Direct Play": "Forcer la lecture directe",
    "Forced": "Forcé",
    "Format": "Format",
    "Forward": "Avancer",
    "GENRE": "GENRE",
    "GENRES": "GENRES",
    "General": "Général",
    "Genre": "Genre",
    "Genres": "Genres",
    "Genres:": "Genres :",
    "Go Back": "Retour",
    "Go to Settings to configure Jellyseerr.": "Veuillez configurer Jellyseerr dans les paramètres.",
    "Go to Settings to log in to Jellyseerr.": "Veuillez vous connecter à Jellyseerr dans les paramètres.",
    "Gray": "Gris",
    "Green": "Vert",
    "Grey": "Gris",
    "Grid direction": "Direction de la grille",
    "H.264 transcoding fallback failed.": "L'alternative H.264 a échoué.",
    "HD + 4K AVAILABLE": "HD + 4K DISPONIBLES",
    "HD AVAILABLE": "HD DISPONIBLE",
    "HD AVAILABLE • 4K DECLINED": "HD DISPO • 4K REJETÉE",
    "HD DECLINED": "HD REJETÉE",
    "HD DECLINED • 4K AVAILABLE": "HD REJETÉE • 4K DISPO",
    "HD PARTIAL • 4K PENDING": "HD PARTIELLE • 4K EN ATTENTE",
    "HD PARTIAL • 4K PROCESSING": "HD PARTIELLE • 4K EN COURS",
    "HD PARTIALLY AVAILABLE": "HD PARTIELLEMENT DISPONIBLE",
    "HD PENDING": "HD EN ATTENTE",
    "HD PENDING • 4K PARTIAL": "HD EN ATTENTE • 4K PARTIELLE",
    "HD PENDING • 4K PROCESSING": "HD EN ATTENTE • 4K EN COURS",
    "HD PROCESSING": "HD EN COURS",
    "HD PROCESSING • 4K PARTIAL": "HD EN COURS • 4K PARTIELLE",
    "HD PROCESSING • 4K PENDING": "HD EN COURS • 4K EN ATTENTE",
    "HDR": "HDR",
    "Halloween": "Halloween",
    "Heavy": "Lourd",
    "Hidden": "Masqué",
    "Hidden libraries are removed from all Jellyfin clients. This is a server-level setting.": "Les bibliothèques masquées le sont pour tous les appareils (réglage serveur).",
    "Hide": "Masquer",
    "Hide Libraries": "Masquer les bibliothèques",
    "Hide Unwatched Count": "Masquer le compteur d'inédits",
    "Higher": "Plus haut",
    "Home": "Accueil",
    "Home Backdrop Blur": "Flou d'arrière-plan (accueil)",
    "Home Row Backdrops": "Fonds des lignes d'accueil",
    "Home Screen": "Écran d'accueil",
    "Huge": "Énorme",
    "Image Type": "Type d'image",
    "Image size": "Taille d'image",
    "Image type": "Type d'image",
    "Indigo": "Indigo",
    "Info": "Info",
    "Initiating Quick Connect...": "Connexion rapide...",
    "Instant": "Instantané",
    "Intro Action": "Action sur l'intro",
    "Item": "Élément",
    "Item Count": "Nombre d'éléments",
    "Items": "Éléments",
    "Items in Collection": "Titres de la collection",
    "Jellyseerr": "Jellyseerr",
    "Jellyseerr is not authenticated.": "Jellyseerr non authentifié.",
    "Jellyseerr is not configured": "Jellyseerr non configuré",
    "Jellyseerr is not enabled.": "Jellyseerr désactivé.",
    "Keep Request": "Conserver la demande",
    "Keyword": "Mot-clé",
    "Keywords": "Mots-clés",
    "Known for:": "Rôles notables :",
    "LIBRARIES": "BIBLIOTHÈQUES",
    "Language": "Langue",
    "Large": "Grand",
    "Last Air Date": "Dernière diffusion",
    "Latest in {libraryTitle}": "Nouveautés : {libraryTitle}",
    "Left Sidebar": "Barre latérale",
    "Libraries": "Bibliothèques",
    "Library": "Bibliothèque",
    "Library Backdrops": "Arrière-plans",
    "Light": "Léger",
    "Live TV Guide": "Guide TV",
    "Loading Recordings...": "Chargement des enregistrements...",
    "Loading TV Guide...": "Chargement du guide TV...",
    "Loading libraries...": "Chargement des bibliothèques...",
    "Loading playlists…": "Chargement des playlists…",
    "Loading requests...": "Chargement des demandes...",
    "Loading server options...": "Chargement des options...",
    "Loading trailer...": "Chargement de la bande-annonce...",
    "Loading your library...": "Chargement de la bibliothèque...",
    "Loading...": "Chargement...",
    "Log In": "Se connecter",
    "Logging in via Moonfin plugin...": "Connexion via Moonfin...",
    "Logging in...": "Connexion...",
    "Logging options": "Options de log",
    "Login failed:": "Échec de la connexion :",
    "Logo": "Logo",
    "Lower": "Plus bas",
    "MDBList Ratings": "Notes MDBList",
    "MOVIE": "FILM",
    "Magenta": "Magenta",
    "Manual Login": "Connexion manuelle",
    "Mark Watched": "Marquer comme vu",
    "Max Bitrate": "Débit max",
    "Max Rating": "Note max",
    "Maximum": "Maximum",
    "Maximum Bitrate": "Débit maximum",
    "Media Info": "Infos média",
    "Media Type": "Type de média",
    "Medium": "Moyen",
    "Merge Continue Watching & Next Up": "Fusionner 'Reprendre' et 'À suivre'",
    "Middle": "Milieu",
    "Minimal": "Minimal",
    "Model": "Modèle",
    "Model and hardware info": "Infos matériel",
    "Mono": "Mono",
    "Moonfin Logo": "Logo Moonfin",
    "Moonfin Plugin": "Plugin Moonfin",
    "Moonfin User": "Utilisateur Moonfin",
    "Moonfin connection failed:": "Échec de connexion Moonfin :",
    "Moonfin plugin and integrations": "Plugin et intégrations Moonfin",
    "Moonfin plugin found but no session. Please log in.": "Plugin détecté. Veuillez vous connecter.",
    "More Like This": "Titres similaires",
    "Movie": "Film",
    "Movies": "Films",
    "Movies & TV Shows": "Films et séries",
    "Movies Only": "Films uniquement",
    "Multi-Server": "Multi-serveur",
    "Mute Trailers": "Bandes-annonces muettes",
    "Mute trailer previews in the featured media bar": "Silence à la une",
    "My Media": "Ma collection",
    "My Requests": "Mes demandes",
    "NOT REQUESTED": "NON DEMANDÉ",
    "Name": "Nom",
    "Navigate": "Naviguer",
    "Navigate to an item to see details": "Sélectionnez un titre pour les détails",
    "Navigation Bar": "Barre de navigation",
    "Navigation Style": "Style de navigation",
    "Navy": "Bleu marine",
    "Network": "Chaîne",
    "Networks": "Chaînes",
    "Never": "Jamais",
    "New Playlist": "Nouvelle playlist",
    "Next": "Suivant",
    "Next Day ▶": "Jour suivant ▶",
    "Next Up": "À suivre",
    "Next Up Behavior": "Comportement de 'À suivre'",
    "No Radarr/Sonarr server configured for {mediaType} in Jellyseerr": "Aucun serveur configuré pour {mediaType}",
    "No channels available": "Aucune chaîne",
    "No content found": "Aucun contenu",
    "No description available.": "Aucune description disponible.",
    "No details available": "Aucun détail disponible",
    "No favorite channels": "Aucune chaîne favorite",
    "No favorites found": "Aucun favori trouvé",
    "No genre selected": "Aucun genre sélectionné",
    "No genres found": "Aucun genre trouvé",
    "No items found": "Aucun élément trouvé",
    "No library selected": "Aucune bibliothèque sélectionnée",
    "No media info available": "Aucune info média disponible",
    "No pages found": "Aucune page trouvée",
    "No playlists found": "Aucune playlist trouvée",
    "No recordings found": "Aucun enregistrement trouvé",
    "No remote subtitles found": "Aucun sous-titre trouvé",
    "No requests found": "Aucune demande trouvée",
    "No results found": "Aucun résultat trouvé",
    "No scheduled recordings": "Aucun enregistrement prévu",
    "None": "Aucun",
    "Normal": "Normal",
    "Not Available": "Indisponible",
    "Not connected": "Non connecté",
    "Not connected to a Jellyfin server": "Non connecté au serveur",
    "Not logged in": "Non connecté",
    "Not supported": "Non supporté",
    "Nothing selected": "Rien de sélectionné",
    "OK": "OK",
    "OK Toggle info": "OK Infos",
    "Off": "Désactivé",
    "Offset": "Décalage",
    "On": "Activé",
    "Only show age-appropriate backdrops": "Fonds d'écran adaptés à l'âge",
    "Opacity, color, and avatar": "Opacité, couleur et avatar",
    "Opening comic...": "Ouverture...",
    "Orange": "Orange",
    "Outro Action": "Action de fin",
    "Overview": "Résumé",
    "Overview unavailable.": "Résumé indisponible.",
    "PARTIALLY AVAILABLE": "PARTIELLEMENT DISPONIBLE",
    "PENDING": "EN ATTENTE",
    "PROCESSING": "EN COURS",
    "Page": "Page",
    "Partial": "Partiel",
    "Partially Available": "Partiellement disponible",
    "Password": "Mot de passe",
    "Password (leave empty if none)": "Mot de passe (facultatif)",
    "Pause": "Pause",
    "Pending": "En attente",
    "People": "Personnes",
    "Person": "Personne",
    "Person not found": "Inconnu",
    "Pink": "Rose",
    "Platform": "Plateforme",
    "Play": "Lire",
    "Play Method": "Méthode de lecture",
    "Play Now": "Lire maintenant",
    "Play background music on detail pages": "Musique de fond (détails)",
    "Play in Moonfin": "Lire dans Moonfin",
    "Play theme music when browsing home screen items": "Musique sur l'accueil",
    "Playback": "Lecture",
    "Playback Error": "Erreur de lecture",
    "Playback Information": "Infos de lecture",
    "Playback Speed": "Vitesse",
    "Playback failed.": "Échec de la lecture.",
    "Playback failed. The file format may not be supported.": "Échec : format peut-être non supporté.",
    "Playback was aborted.": "La lecture a été interrompue.",
    "Playback, bitrate, and seeking": "Lecture, débit et recherche",
    "Player": "Lecteur",
    "Playlist name": "Nom de la playlist",
    "Please configure Jellyseerr in Settings": "Configurez Jellyseerr dans les paramètres",
    "Please enter username and password": "Nom d'utilisateur et mot de passe requis",
    "Plugin": "Plugin",
    "Plugin Status": "Statut du plugin",
    "Plugin Version": "Version du plugin",
    "Plugin connection and login": "Connexion du plugin",
    "Popular Movies": "Films populaires",
    "Popular TV Shows": "Séries populaires",
    "Position": "Position",
    "Poster": "Affiche",
    "Poster Size": "Taille des affiches",
    "Prefer Transcoding": "Préférer le transcodage",
    "Press BACK to close": "Retour pour fermer",
    "Press Back to close": "Retour pour fermer",
    "Previous": "Précédent",
    "Processing": "En cours",
    "Purple": "Violet",
    "Quality": "Qualité",
    "Quality Profile": "Profil de qualité",
    "Quick Connect": "Connexion rapide",
    "Quick Connect authorized! Adding user...": "Autorisé ! Ajout...",
    "Quick Connect authorized! Signing in...": "Autorisé ! Connexion...",
    "Quick Connect failed. Try password login instead.": "Échec. Utilisez votre mot de passe.",
    "Quick Connect is not available on this server. Use password login.": "Indisponible sur ce serveur.",
    "Rating display settings": "Affichage des notes",
    "Rating:": "Note :",
    "Read": "Lire",
    "Recommendations": "Recommandations",
    "Recordings": "Enregistrements",
    "Red": "Rouge",
    "Reduce brightness after inactivity to prevent screen burn-in": "Réduire l'éclat en cas d'inactivité",
    "Release Date": "Date de sortie",
    "Remove": "Supprimer",
    "Remove User": "Supprimer l'utilisateur",
    "Removed from playlist": "Retiré",
    "Request": "Demander",
    "Request More": "En demander plus",
    "Request Options": "Options de demande",
    "Request failed": "Échec de la demande",
    "Request transcoded streams when available": "Flux transcodés si possible",
    "Requested:": "Demandé :",
    "Reset": "Réinitialiser",
    "Reset to Default": "Valeurs par défaut",
    "Resolution": "Résolution",
    "Restart": "Redémarrer",
    "Restart the app to apply the new language": "Redémarrez pour changer de langue",
    "Resume": "Reprendre",
    "Retry": "Réessayer",
    "Revenue": "Recettes",
    "Rewind": "Retour",
    "Rows and library visibility": "Visibilité des lignes",
    "Runtime": "Durée",
    "SERIES": "SÉRIE",
    "Sample Rate": "Échantillonnage",
    "Save": "Enregistrer",
    "Saving...": "Enregistrement...",
    "Scheduled": "Programmé",
    "Scheduled:": "Programmé :",
    "Screensaver": "Économiseur d'écran",
    "Screensaver Type": "Type d'économiseur",
    "Search": "Rechercher",
    "Search for content": "Rechercher un contenu",
    "Search movies, shows, music, and more...": "Films, séries, musique...",
    "Searching...": "Recherche...",
    "Season": "Saison",
    "Season {number} Episodes": "Épisodes - Saison {number}",
    "Seasonal Effect": "Effet saisonnier",
    "Seasonal effects and theme music": "Effets et thèmes musicaux",
    "Seasons": "Saisons",
    "Seek Step": "Intervalle de saut",
    "Select All": "Tout sélectionner",
    "Select Audio Track": "Piste audio",
    "Select Seasons": "Saisons",
    "Select Subtitle": "Sous-titres",
    "Select Version": "Version",
    "Select quality to request": "Qualité souhaitée",
    "Send logs to Jellyfin server for troubleshooting": "Envoyer les logs pour dépannage",
    "Series": "Séries",
    "Server": "Serveur",
    "Server Address": "Adresse du serveur",
    "Server Logging": "Logs serveur",
    "Server URL": "URL Serveur",
    "Server Version": "Version serveur",
    "Server version {version} is not supported. Minimum: {minimum}.": "Version {version} non supportée (Min: {minimum}).",
    "Servers & Users": "Serveurs et utilisateurs",
    "Settings": "Paramètres",
    "Settings Sync": "Synchro des réglages",
    "Shadow Color": "Couleur de l'ombre",
    "Shadow Opacity": "Opacité de l'ombre",
    "Shadow Size (Blur)": "Taille de l'ombre",
    "Show": "Afficher",
    "Show Clock": "Afficher l'horloge",
    "Show Description on Pause": "Infos sur pause",
    "Show Favorites Button": "Bouton Favoris",
    "Show Featured Bar": "Bandeau à la une",
    "Show Genres Button": "Bouton Genres",
    "Show Less": "Moins",
    "Show Libraries in Toolbar": "Bibliothèques dans la barre d'outils",
    "Show MDBList ratings on media details and featured bar": "Notes MDBList (accueil et détails)",
    "Show More": "Plus",
    "Show Rating Labels": "Libellés des notes",
    "Show Shuffle Button": "Bouton Aléatoire",
    "Show TMDB ratings on individual episodes": "Notes TMDB par épisode",
    "Show background art when browsing rows on the home screen": "Images de fond sur l'accueil",
    "Show favorites button in navigation bar": "Favoris dans la navigation",
    "Show genres button in navigation bar": "Genres dans la navigation",
    "Show library shortcuts in navigation bar": "Raccourcis dans la navigation",
    "Show or hide clock on home screen": "Horloge sur l'accueil",
    "Show series artwork instead of individual episode images": "Visuels de série pour les épisodes",
    "Show shuffle button in navigation bar": "Aléatoire dans la navigation",
    "Shuffle": "Aléatoire",
    "Shuffle Content Type": "Type d'aléatoire",
    "Sign In": "Connexion",
    "Sign In As {name}": "Connexion : {name}",
    "Sign Out": "Déconnexion",
    "Sign Out All Users": "Déconnecter tous les utilisateurs",
    "Signing in...": "Connexion...",
    "Similar Artists": "Artistes similaires",
    "Similar Series": "Séries similaires",
    "Similar Titles": "Titres similaires",
    "Size": "Taille",
    "Size, position, color, and background": "Taille, position et style",
    "Skip Forward Length": "Saut avant",
    "Skip Intro": "Passer l'introduction",
    "Skip codec checks and always attempt DirectPlay (debug)": "Forcer DirectPlay (débogage)",
    "Slate": "Ardoise",
    "Slightly Large": "Assez grand",
    "Slightly Small": "Assez petit",
    "Slightly enlarge cards when focused": "Agrandir la sélection",
    "Small": "Petit",
    "Songs": "Morceaux",
    "Sort & Filter": "Trier et filtrer",
    "Sort By": "Trier par",
    "Source": "Source",
    "Speed": "Vitesse",
    "Spring": "Printemps",
    "Starting in {countdown}s": "Départ dans {countdown}s",
    "Status": "Statut",
    "Stereo": "Stéréo",
    "Strong": "Fort",
    "Studio": "Studio",
    "Style, buttons, and shortcuts": "Style et raccourcis",
    "Subtitle": "Sous-titre",
    "Subtitle Appearance": "Style des sous-titres",
    "Subtitle Offset": "Décalage des sous-titres",
    "Subtitle Position": "Position des sous-titres",
    "Subtitle Size": "Taille des sous-titres",
    "Subtitles": "Sous-titres",
    "Summer": "Été",
    "Supported formats and codecs": "Formats supportés",
    "Switch": "Changer",
    "TMDB Score": "Score TMDB",
    "TV Series": "Séries",
    "TV Show": "Série",
    "TV Shows": "Séries",
    "TV Shows Only": "Séries uniquement",
    "TV shows": "séries",
    "Teal": "Sarcelle",
    "Text Color": "Couleur du texte",
    "Text Opacity": "Opacité du texte",
    "The video format is not supported by this TV.": "Format vidéo non supporté par ce téléviseur.",
    "The video source is not supported.": "Source vidéo non supportée.",
    "Theme Music": "Thème musical",
    "Theme Music Volume": "Volume du thème",
    "Theme Music on Home Rows": "Thèmes sur l'accueil",
    "Themes & Effects": "Thèmes et effets",
    "Thumb": "Vignette",
    "Timeout": "Délai expiré",
    "Tizen Version": "Version Tizen",
    "Today": "Aujourd'hui",
    "Toggle info": "Afficher les infos",
    "Top Bar": "Barre supérieure",
    "Track": "Piste",
    "Tracks": "Pistes",
    "Trailer": "Bande-annonce",
    "Trailer Preview": "Aperçu bande-annonce",
    "Transcode Reason": "Raison du transcodage",
    "Transcoding failed after retry. Try restarting the app.": "Échec du transcodage. Redémarrez l'application.",
    "Transcoding failed. The server may not support this format.": "Échec : format non supporté par le serveur.",
    "Trending Now": "Tendances",
    "Try a different search term": "Essayez une autre recherche",
    "Trying {url}...": "Tentative {url}...",
    "Type": "Type",
    "UI Color": "Couleur de l'interface",
    "UI Elements": "Éléments d'interface",
    "UI Opacity": "Opacité de l'interface",
    "UI Scale": "Échelle de l'interface",
    "UP NEXT": "À SUIVRE",
    "Unavailable": "Indisponible",
    "Unified Library Mode": "Mode bibliothèque unifiée",
    "Unified library settings": "Réglages unifiés",
    "Unknown": "Inconnu",
    "Unpause Rewind": "Retour arrière à la reprise",
    "Unwatched": "Non vus",
    "Upcoming Movies": "Sorties cinéma",
    "Upcoming TV Shows": "Séries à venir",
    "Update Available": "Mise à jour disponible",
    "Use Defaults": "Par défaut",
    "Use Password Instead": "Utiliser le mot de passe",
    "Use Series Thumbnails": "Vignettes de séries",
    "Use client-side rendering for bitmap subtitles (PGS, DVB, DVD)": "Rendu client (PGS, DVB, DVD)",
    "User": "Utilisateur",
    "User Avatar Opacity": "Opacité de l'avatar",
    "Username": "Utilisateur",
    "Version": "Version",
    "Version and platform": "Version et plateforme",
    "Version and sync info": "Infos version et synchro",
    "Video": "Vidéo",
    "Video Bitrate": "Débit vidéo",
    "Video Codecs": "Codecs vidéo",
    "Video, audio, and subtitle options": "Vidéo, audio et sous-titres",
    "Visible": "Visible",
    "Waiting for authorization...": "En attente d'autorisation...",
    "Watch Now": "Regarder",
    "Watch Trailer": "Bande-annonce",
    "Watched": "Vu",
    "Watched Indicators": "Indicateurs de lecture",
    "Watched Only": "Vus uniquement",
    "White": "Blanc",
    "Winter": "Hiver",
    "Writers": "Scénaristes",
    "Year:": "Année :",
    "Yellow": "Jaune",
    "You will need to sign in again to use this account.": "Veuillez vous reconnecter pour ce compte.",
    "age": "âge",
    "and": "et",
    "channels": "chaînes",
    "episode": "épisode",
    "episodes": "épisodes",
    "genres": "genres",
    "items": "éléments",
    "movies": "films",
    "webOS Version": "Version webOS",
    "{count} favorites sorted by {sortLabel}": "{count} favoris par {sortLabel}",
    "{count} genres sorted by {sortLabel}": "{count} genres par {sortLabel}",
    "{count} items": "{count} éléments",
    "{seerrLabel} (Seerr v3+)": "{seerrLabel} (Seerr v3+)",
    "{seerrLabel} Password": "Mot de passe {seerrLabel}",
    "{seerrLabel} URL": "URL {seerrLabel}",
    "{seerrLabel} Username": "Utilisateur {seerrLabel}",
    "{seerrLabel} connection is managed through the Moonfin plugin. Log in above if prompted.": "Connexion gérée via Moonfin. Connectez-vous ci-dessus.",
    "{seerrLabel} connection status": "Statut de connexion {seerrLabel}",
    "◀ Previous Day": "◀ Jour précédent",
    "◀ ▶ Navigate": "◀ ▶ Naviguer",
    "◀ ▶ to re-order · DEL to remove": "◀ ▶ réorganiser · DEL supprimer"
}